paramclass_pyomo/__init__.py
paramclass_pyomo/abstractblock.py
paramclass_pyomo/linker.py
paramclass_pyomo/proxycomponent.py
paramclass_pyomo-1.0.1.dist-info/METADATA
paramclass_pyomo-1.0.1.dist-info/WHEEL
paramclass_pyomo-1.0.1.dist-info/top_level.txt
paramclass_pyomo-1.0.1.dist-info/RECORD
